jsfuzz/inspector.py
jsfuzz-1.0.0.dist-info/LICENSE
jsfuzz-1.0.0.dist-info/METADATA
jsfuzz-1.0.0.dist-info/WHEEL
jsfuzz-1.0.0.dist-info/RECORD
