Metadata-Version: 2.1
Name: jsfuzz
Version: 1.0.0
Summary: Inspect json data and fuzzy search for values or key names
Home-page: https://github.com/3cham/jsfuzz.git
License: MIT
Author: Tung Dang
Author-email: tung.dang@otto.de
Requires-Python: >=3.9
Classifier: License :: OSI Approved :: MIT License
Classifier: Programming Language :: Python :: 3
Classifier: Programming Language :: Python :: 3.9
Classifier: Programming Language :: Python :: 3.10
Classifier: Programming Language :: Python :: 3.11
Requires-Dist: rapidfuzz (>=3.0.0,<4.0.0)
